rubico/__init__.py
rubico/bot.py
rubico/client.py
rubico/commands.py
rubico/context.py
rubico/dispatcher.py
rubico/filters.py
rubico/force_join.py
rubico/handlers.py
rubico/keyboard.py
rubico/logger.py
rubico/middlewares.py
rubico/steps.py
rubico/storage.py
rubico/updater.py
rubico-1.2.0.dist-info/METADATA
rubico-1.2.0.dist-info/WHEEL
rubico-1.2.0.dist-info/top_level.txt
rubico-1.2.0.dist-info/RECORD
