Metadata-Version: 2.4
Name: rubico
Version: 1.2.0
Summary: Professional Rubika Bot Framework
Author: Rubico Team
Requires-Dist: requests
Dynamic: author
Dynamic: requires-dist
Dynamic: summary
